{
    "key": "group_660c1f9cd76c1",
    "title": "Video",
    "fields": [
        {
            "key": "field_660c1f9cb0f12",
            "label": "Video",
            "name": "video",
            "aria-label": "",
            "type": "clone",
            "instructions": "",
            "required": 0,
            "conditional_logic": 0,
            "wrapper": {
                "width": "",
                "class": "",
                "id": ""
            },
            "clone": [
                "group_65fa8e76c8cce"
            ],
            "display": "seamless",
            "layout": "block",
            "prefix_label": 0,
            "prefix_name": 0
        }
    ],
    "location": [
        [
            {
                "param": "block",
                "operator": "==",
                "value": "acf\/video"
            }
        ]
    ],
    "menu_order": 0,
    "position": "normal",
    "style": "default",
    "label_placement": "top",
    "instruction_placement": "label",
    "hide_on_screen": "",
    "active": true,
    "description": "",
    "show_in_rest": 0,
    "modified": 1712082044
}
